{
    "certificados": [
        {
            "chave": "lb8dtldo",
            "nome": "Stephanie Casseano de Sousa",
            "horas": 3,
            "responsavel": "Marco Antonio Sanches Anastacio",
            "data_emissao": "20 de setembro de 2024",
            "campus": "Anália Franco",
            "rgm": 38354250,
            "natureza": "Reunião de avaliação de curso (MEC)"
        },
        {
            "chave": "bgzrjgmo",
            "nome": "Guilherme Oliveira de Souza",
            "horas": 3,
            "responsavel": "Marco Antonio Sanches Anastacio",
            "data_emissao": "20 de setembro de 2024",
            "campus": "Anália Franco",
            "rgm": 33819777,
            "natureza": "Reunião de avaliação de curso (MEC)"
        },
        {
            "chave": "71uld52i",
            "nome": "Giovanna Berni da Silva",
            "horas": 3,
            "responsavel": "Marco Antonio Sanches Anastacio",
            "data_emissao": "20 de setembro de 2024",
            "campus": "Anália Franco",
            "rgm": 30013941,
            "natureza": "Reunião de avaliação de curso (MEC)"
        },
        {
            "chave": "gql65gjo",
            "nome": "Gustavo Nunes Soares",
            "horas": 3,
            "responsavel": "Marco Antonio Sanches Anastacio",
            "data_emissao": "20 de setembro de 2024",
            "campus": "Anália Franco",
            "rgm": 33574634,
            "natureza": "Reunião de avaliação de curso (MEC)"
        },
        {
            "chave": "8u9scyad",
            "nome": "Victoria Andreozzi Gualano ",
            "horas": 3,
            "responsavel": "Marco Antonio Sanches Anastacio",
            "data_emissao": "20 de setembro de 2024",
            "campus": "Anália Franco",
            "rgm": 38624133,
            "natureza": "Reunião de avaliação de curso (MEC)"
        },
        {
            "chave": "pvlprfqn",
            "nome": "Otavio Alves Cruz de Oliveira Santos",
            "horas": 3,
            "responsavel": "Marco Antonio Sanches Anastacio",
            "data_emissao": "20 de setembro de 2024",
            "campus": "Anália Franco",
            "rgm": 38624133,
            "natureza": "Reunião de avaliação de curso (MEC)"
        },
        {
            "chave": "qaiy7yse",
            "nome": "Vinicius Leonardo da Silva ",
            "horas": 3,
            "responsavel": "Marco Antonio Sanches Anastacio",
            "data_emissao": "20 de setembro de 2024",
            "campus": "Anália Franco",
            "rgm": 38376784,
            "natureza": "Reunião de avaliação de curso (MEC)"
        },
        {
            "chave": "a2oad5wv",
            "nome": "Larissa Torres Ferreira",
            "horas": 3,
            "responsavel": "Marco Antonio Sanches Anastacio",
            "data_emissao": "20 de setembro de 2024",
            "campus": "Anália Franco",
            "rgm": 37416341,
            "natureza": "Reunião de avaliação de curso (MEC)"
        },
        {
            "chave": "eypohtsv",
            "nome": "Diogo Santos Rodrigues",
            "horas": 3,
            "responsavel": "Marco Antonio Sanches Anastacio",
            "data_emissao": "20 de setembro de 2024",
            "campus": "Santo Amaro",
            "rgm": 33373582,
            "natureza": "Reunião de avaliação de curso (MEC)"
        },
        {
            "chave": "ogujsft0",
            "nome": "Leonardo Souto Ferrarezi",
            "horas": 3,
            "responsavel": "Marco Antonio Sanches Anastacio",
            "data_emissao": "20 de setembro de 2024",
            "campus": "Santo Amaro",
            "rgm": 33955263,
            "natureza": "Reunião de avaliação de curso (MEC)"
        },
        {
            "chave": "0vqrbcfw",
            "nome": "Makaya António Afonso",
            "horas": 3,
            "responsavel": "Marco Antonio Sanches Anastacio",
            "data_emissao": "20 de setembro de 2024",
            "campus": "Santo Amaro",
            "rgm": 32640072,
            "natureza": "Reunião de avaliação de curso (MEC)"
        },
        {
            "chave": "pv2xoxr0",
            "nome": "Raisson Abrantes de Souza",
            "horas": 3,
            "responsavel": "Marco Antonio Sanches Anastacio",
            "data_emissao": "20 de setembro de 2024",
            "campus": "Santo Amaro",
            "rgm": 34700048,
            "natureza": "Reunião de avaliação de curso (MEC)"
        },
        {
            "chave": "rcgf7x28",
            "nome": "João Filipe Alves de Souza",
            "horas": 3,
            "responsavel": "Marco Antonio Sanches Anastacio",
            "data_emissao": "20 de setembro de 2024",
            "campus": "Santo Amaro",
            "rgm": 34700048,
            "natureza": "Reunião de avaliação de curso (MEC)"
        },
        {
            "chave": "od670ydu",
            "nome": "Henrique dos Santos Santana",
            "horas": 3,
            "responsavel": "Marco Antonio Sanches Anastacio",
            "data_emissao": "20 de setembro de 2024",
            "campus": "Santo Amaro",
            "rgm": 35737981,
            "natureza": "Reunião de avaliação de curso (MEC)"
        },
        {
            "chave": "mz8hl1c3",
            "nome": "Paulo Ricardo Cavalcante dos Santos",
            "horas": 3,
            "responsavel": "Marco Antonio Sanches Anastacio",
            "data_emissao": "20 de setembro de 2024",
            "campus": "Santo Amaro",
            "rgm": 34771611,
            "natureza": "Reunião de avaliação de curso (MEC)"
        },
        {
            "chave": "o3yri18s",
            "nome": "Isabela Soares dos Santos",
            "horas": 3,
            "responsavel": "Marco Antonio Sanches Anastacio",
            "data_emissao": "20 de setembro de 2024",
            "campus": "Santo Amaro",
            "rgm": 38613972,
            "natureza": "Reunião de avaliação de curso (MEC)"
        },
        {
            "chave": "8tniv5bt",
            "nome": "João Victor Guinoza dos Santos",
            "horas": 3,
            "responsavel": "Marco Antonio Sanches Anastacio",
            "data_emissao": "20 de setembro de 2024",
            "campus": "Santo Amaro",
            "rgm": 33502048,
            "natureza": "Reunião de avaliação de curso (MEC)"
        },
        {
            "chave": "bnl0b830",
            "nome": "Kennedy Silva Pereira",
            "horas": 3,
            "responsavel": "Marco Antonio Sanches Anastacio",
            "data_emissao": "20 de setembro de 2024",
            "campus": "Santo Amaro",
            "rgm": 34481427,
            "natureza": "Reunião de avaliação de curso (MEC)"
        },
        {
            "chave": "hjoxa2zu",
            "nome": "Gabriel Santana Camargo",
            "horas": 3,
            "responsavel": "Marco Antonio Sanches Anastacio",
            "data_emissao": "20 de setembro de 2024",
            "campus": "Santo Amaro",
            "rgm": 33544867,
            "natureza": "Reunião de avaliação de curso (MEC)"
        },
        {
            "chave": "s9w1iz38",
            "nome": "Fabiana Garcia Seguette",
            "horas": 3,
            "responsavel": "Marco Antonio Sanches Anastacio",
            "data_emissao": "20 de setembro de 2024",
            "campus": "Anália Franco",
            "rgm": 33574634,
            "natureza": "Reunião de avaliação de curso (MEC)"
        }
    ]
}
